{"metadata": {"fetched_at": "2026-07-18T15:18:23.086347", "area_id": "commune_19571184", "source": "open-meteo/archive-api (batch)"}, "records": [{"date": "2014-03-06", "area_id": "commune_19571184", "lat": 21.3182894, "lon": 103.2995758, "year": 2014, "month": 3, "day": 6, "temperature_2m_max": 26.7, "temperature_2m_min": 12.3, "temperature_2m_mean": 19.0, "apparent_temperature_max": 25.0, "apparent_temperature_min": 11.9, "apparent_temperature_mean": 18.1, "precipitation_sum": 0.0, "rain_sum": 0.0, "precipitation_hours": 0.0, "weather_code": 2.0, "shortwave_radiation_sum": 22.18, "et0_fao_evapotranspiration": 4.62, "daylight_duration": 42559.16, "sunshine_duration": 39858.67, "uv_index_max": null, "wind_speed_10m_max": 13.5, "wind_gusts_10m_max": 46.4, "wind_direction_10m_dominant": 200.0, "relative_humidity_2m_mean": 59.0, "surface_pressure_mean": 854.5}]}