{"metadata": {"fetched_at": "2026-07-18T15:18:23.260258", "area_id": "commune_19571184", "source": "open-meteo/archive-api (batch)"}, "records": [{"date": "2016-07-26", "area_id": "commune_19571184", "lat": 21.3182894, "lon": 103.2995758, "year": 2016, "month": 7, "day": 26, "temperature_2m_max": 26.8, "temperature_2m_min": 16.9, "temperature_2m_mean": 21.2, "apparent_temperature_max": 31.6, "apparent_temperature_min": 18.8, "apparent_temperature_mean": 24.2, "precipitation_sum": 2.3, "rain_sum": 2.3, "precipitation_hours": 5.0, "weather_code": 53.0, "shortwave_radiation_sum": 24.49, "et0_fao_evapotranspiration": 4.67, "daylight_duration": 47438.86, "sunshine_duration": 43500.19, "uv_index_max": null, "wind_speed_10m_max": 5.0, "wind_gusts_10m_max": 19.4, "wind_direction_10m_dominant": 210.0, "relative_humidity_2m_mean": 84.0, "surface_pressure_mean": 853.3}]}