{"metadata": {"fetched_at": "2026-07-18T15:17:40.675894", "area_id": "commune_19537916", "source": "open-meteo/archive-api (batch)"}, "records": [{"date": "2010-01-20", "area_id": "commune_19537916", "lat": 22.0619828, "lon": 102.5143555, "year": 2010, "month": 1, "day": 20, "temperature_2m_max": 24.2, "temperature_2m_min": 10.9, "temperature_2m_mean": 17.4, "apparent_temperature_max": 24.7, "apparent_temperature_min": 10.6, "apparent_temperature_mean": 17.7, "precipitation_sum": 0.0, "rain_sum": 0.0, "precipitation_hours": 0.0, "weather_code": 3.0, "shortwave_radiation_sum": 17.17, "et0_fao_evapotranspiration": 3.12, "daylight_duration": 39568.58, "sunshine_duration": 38813.38, "uv_index_max": null, "wind_speed_10m_max": 7.2, "wind_gusts_10m_max": 15.1, "wind_direction_10m_dominant": 139.0, "relative_humidity_2m_mean": 71.0, "surface_pressure_mean": 900.2}]}