{"metadata": {"fetched_at": "2026-07-18T15:17:41.503059", "area_id": "commune_19537916", "source": "open-meteo/archive-api (batch)"}, "records": [{"date": "2021-03-28", "area_id": "commune_19537916", "lat": 22.0619828, "lon": 102.5143555, "year": 2021, "month": 3, "day": 28, "temperature_2m_max": 28.2, "temperature_2m_min": 18.3, "temperature_2m_mean": 23.1, "apparent_temperature_max": 30.4, "apparent_temperature_min": 18.1, "apparent_temperature_mean": 24.3, "precipitation_sum": 0.0, "rain_sum": 0.0, "precipitation_hours": 0.0, "weather_code": 1.0, "shortwave_radiation_sum": 19.85, "et0_fao_evapotranspiration": 4.32, "daylight_duration": 44230.42, "sunshine_duration": 41085.48, "uv_index_max": null, "wind_speed_10m_max": 9.0, "wind_gusts_10m_max": 36.7, "wind_direction_10m_dominant": 213.0, "relative_humidity_2m_mean": 61.0, "surface_pressure_mean": 894.2}]}