{"metadata": {"fetched_at": "2026-07-18T15:17:41.032168", "area_id": "commune_19537916", "source": "open-meteo/archive-api (batch)"}, "records": [{"date": "2014-11-12", "area_id": "commune_19537916", "lat": 22.0619828, "lon": 102.5143555, "year": 2014, "month": 11, "day": 12, "temperature_2m_max": 21.3, "temperature_2m_min": 16.6, "temperature_2m_mean": 18.4, "apparent_temperature_max": 24.3, "apparent_temperature_min": 18.7, "apparent_temperature_mean": 20.7, "precipitation_sum": 3.9, "rain_sum": 3.9, "precipitation_hours": 12.0, "weather_code": 53.0, "shortwave_radiation_sum": 9.76, "et0_fao_evapotranspiration": 1.76, "daylight_duration": 40100.61, "sunshine_duration": 24745.16, "uv_index_max": null, "wind_speed_10m_max": 4.7, "wind_gusts_10m_max": 20.9, "wind_direction_10m_dominant": 89.0, "relative_humidity_2m_mean": 96.0, "surface_pressure_mean": 900.0}]}