{"metadata": {"fetched_at": "2026-07-18T15:17:41.665298", "area_id": "commune_19537916", "source": "open-meteo/archive-api (batch)"}, "records": [{"date": "2023-05-24", "area_id": "commune_19537916", "lat": 22.0619828, "lon": 102.5143555, "year": 2023, "month": 5, "day": 24, "temperature_2m_max": 31.2, "temperature_2m_min": 22.1, "temperature_2m_mean": 26.2, "apparent_temperature_max": 34.2, "apparent_temperature_min": 23.3, "apparent_temperature_mean": 28.1, "precipitation_sum": 0.1, "rain_sum": 0.1, "precipitation_hours": 1.0, "weather_code": 51.0, "shortwave_radiation_sum": 25.48, "et0_fao_evapotranspiration": 5.87, "daylight_duration": 47892.27, "sunshine_duration": 44329.32, "uv_index_max": null, "wind_speed_10m_max": 11.6, "wind_gusts_10m_max": 41.4, "wind_direction_10m_dominant": 221.0, "relative_humidity_2m_mean": 59.0, "surface_pressure_mean": 894.7}]}