{"metadata": {"fetched_at": "2026-07-18T15:17:11.089356", "area_id": "commune_19537915", "source": "open-meteo/archive-api (batch)"}, "records": [{"date": "2023-05-23", "area_id": "commune_19537915", "lat": 22.1839144, "lon": 102.581816, "year": 2023, "month": 5, "day": 23, "temperature_2m_max": 36.1, "temperature_2m_min": 22.0, "temperature_2m_mean": 28.5, "apparent_temperature_max": 37.8, "apparent_temperature_min": 23.8, "apparent_temperature_mean": 30.6, "precipitation_sum": 0.0, "rain_sum": 0.0, "precipitation_hours": 0.0, "weather_code": 3.0, "shortwave_radiation_sum": 24.71, "et0_fao_evapotranspiration": 5.86, "daylight_duration": 47879.26, "sunshine_duration": 44603.51, "uv_index_max": null, "wind_speed_10m_max": 11.8, "wind_gusts_10m_max": 36.0, "wind_direction_10m_dominant": 247.0, "relative_humidity_2m_mean": 53.0, "surface_pressure_mean": 939.5}]}