{"metadata": {"fetched_at": "2026-07-18T15:17:11.173998", "area_id": "commune_19537915", "source": "open-meteo/archive-api (batch)"}, "records": [{"date": "2024-07-27", "area_id": "commune_19537915", "lat": 22.1839144, "lon": 102.581816, "year": 2024, "month": 7, "day": 27, "temperature_2m_max": 34.5, "temperature_2m_min": 22.9, "temperature_2m_mean": 28.3, "apparent_temperature_max": 42.2, "apparent_temperature_min": 27.9, "apparent_temperature_mean": 34.2, "precipitation_sum": 0.2, "rain_sum": 0.2, "precipitation_hours": 1.0, "weather_code": 51.0, "shortwave_radiation_sum": 23.81, "et0_fao_evapotranspiration": 5.19, "daylight_duration": 47554.38, "sunshine_duration": 43841.74, "uv_index_max": null, "wind_speed_10m_max": 6.5, "wind_gusts_10m_max": 16.9, "wind_direction_10m_dominant": 186.0, "relative_humidity_2m_mean": 79.0, "surface_pressure_mean": 936.8}]}