{"metadata": {"fetched_at": "2026-07-18T15:17:10.716418", "area_id": "commune_19537915", "source": "open-meteo/archive-api (batch)"}, "records": [{"date": "2018-04-21", "area_id": "commune_19537915", "lat": 22.1839144, "lon": 102.581816, "year": 2018, "month": 4, "day": 21, "temperature_2m_max": 28.4, "temperature_2m_min": 18.7, "temperature_2m_mean": 22.4, "apparent_temperature_max": 33.4, "apparent_temperature_min": 21.6, "apparent_temperature_mean": 26.2, "precipitation_sum": 4.3, "rain_sum": 4.3, "precipitation_hours": 3.0, "weather_code": 63.0, "shortwave_radiation_sum": 13.01, "et0_fao_evapotranspiration": 2.68, "daylight_duration": 45993.9, "sunshine_duration": 21292.46, "uv_index_max": null, "wind_speed_10m_max": 8.7, "wind_gusts_10m_max": 38.9, "wind_direction_10m_dominant": 67.0, "relative_humidity_2m_mean": 92.0, "surface_pressure_mean": 941.6}]}