{"metadata": {"fetched_at": "2026-07-18T15:17:10.514613", "area_id": "commune_19537915", "source": "open-meteo/archive-api (batch)"}, "records": [{"date": "2015-06-30", "area_id": "commune_19537915", "lat": 22.1839144, "lon": 102.581816, "year": 2015, "month": 6, "day": 30, "temperature_2m_max": 31.9, "temperature_2m_min": 22.9, "temperature_2m_mean": 27.7, "apparent_temperature_max": 36.0, "apparent_temperature_min": 27.2, "apparent_temperature_mean": 31.9, "precipitation_sum": 0.0, "rain_sum": 0.0, "precipitation_hours": 0.0, "weather_code": 3.0, "shortwave_radiation_sum": 20.37, "et0_fao_evapotranspiration": 4.52, "daylight_duration": 48505.13, "sunshine_duration": 43115.17, "uv_index_max": null, "wind_speed_10m_max": 10.4, "wind_gusts_10m_max": 37.8, "wind_direction_10m_dominant": 232.0, "relative_humidity_2m_mean": 73.0, "surface_pressure_mean": 939.6}]}