{"metadata": {"fetched_at": "2026-07-18T15:17:10.780891", "area_id": "commune_19537915", "source": "open-meteo/archive-api (batch)"}, "records": [{"date": "2019-03-15", "area_id": "commune_19537915", "lat": 22.1839144, "lon": 102.581816, "year": 2019, "month": 3, "day": 15, "temperature_2m_max": 28.5, "temperature_2m_min": 18.1, "temperature_2m_mean": 22.5, "apparent_temperature_max": 30.5, "apparent_temperature_min": 19.4, "apparent_temperature_mean": 23.8, "precipitation_sum": 0.0, "rain_sum": 0.0, "precipitation_hours": 0.0, "weather_code": 3.0, "shortwave_radiation_sum": 15.52, "et0_fao_evapotranspiration": 3.55, "daylight_duration": 43193.02, "sunshine_duration": 33426.36, "uv_index_max": null, "wind_speed_10m_max": 12.7, "wind_gusts_10m_max": 36.4, "wind_direction_10m_dominant": 111.0, "relative_humidity_2m_mean": 73.0, "surface_pressure_mean": 947.7}]}