{"metadata": {"fetched_at": "2026-07-18T15:15:35.269430", "area_id": "muong_nhe", "source": "open-meteo/archive-api (batch)"}, "records": [{"date": "2015-04-23", "area_id": "muong_nhe", "lat": 22.2169654, "lon": 102.4203498, "year": 2015, "month": 4, "day": 23, "temperature_2m_max": 24.8, "temperature_2m_min": 20.4, "temperature_2m_mean": 21.9, "apparent_temperature_max": 28.4, "apparent_temperature_min": 23.9, "apparent_temperature_mean": 25.5, "precipitation_sum": 17.2, "rain_sum": 17.2, "precipitation_hours": 14.0, "weather_code": 63.0, "shortwave_radiation_sum": 10.46, "et0_fao_evapotranspiration": 2.05, "daylight_duration": 46127.39, "sunshine_duration": 19608.81, "uv_index_max": null, "wind_speed_10m_max": 6.5, "wind_gusts_10m_max": 26.3, "wind_direction_10m_dominant": 103.0, "relative_humidity_2m_mean": 94.0, "surface_pressure_mean": 947.8}]}