{"metadata": {"fetched_at": "2026-07-18T15:15:35.929992", "area_id": "muong_nhe", "source": "open-meteo/archive-api (batch)"}, "records": [{"date": "2024-05-02", "area_id": "muong_nhe", "lat": 22.2169654, "lon": 102.4203498, "year": 2024, "month": 5, "day": 2, "temperature_2m_max": 35.8, "temperature_2m_min": 21.9, "temperature_2m_mean": 28.0, "apparent_temperature_max": 39.7, "apparent_temperature_min": 24.7, "apparent_temperature_mean": 30.6, "precipitation_sum": 0.0, "rain_sum": 0.0, "precipitation_hours": 0.0, "weather_code": 3.0, "shortwave_radiation_sum": 18.48, "et0_fao_evapotranspiration": 4.8, "daylight_duration": 46783.62, "sunshine_duration": 39339.78, "uv_index_max": null, "wind_speed_10m_max": 19.1, "wind_gusts_10m_max": 51.5, "wind_direction_10m_dominant": 141.0, "relative_humidity_2m_mean": 61.0, "surface_pressure_mean": 939.5}]}