{"metadata": {"fetched_at": "2026-07-18T15:15:35.517067", "area_id": "muong_nhe", "source": "open-meteo/archive-api (batch)"}, "records": [{"date": "2018-09-16", "area_id": "muong_nhe", "lat": 22.2169654, "lon": 102.4203498, "year": 2018, "month": 9, "day": 16, "temperature_2m_max": 32.2, "temperature_2m_min": 21.3, "temperature_2m_mean": 26.2, "apparent_temperature_max": 37.6, "apparent_temperature_min": 25.1, "apparent_temperature_mean": 31.3, "precipitation_sum": 0.0, "rain_sum": 0.0, "precipitation_hours": 0.0, "weather_code": 3.0, "shortwave_radiation_sum": 22.36, "et0_fao_evapotranspiration": 4.65, "daylight_duration": 44153.87, "sunshine_duration": 43159.32, "uv_index_max": null, "wind_speed_10m_max": 4.7, "wind_gusts_10m_max": 23.0, "wind_direction_10m_dominant": 301.0, "relative_humidity_2m_mean": 82.0, "surface_pressure_mean": 939.1}]}