{"metadata": {"fetched_at": "2026-07-18T15:15:35.802066", "area_id": "muong_nhe", "source": "open-meteo/archive-api (batch)"}, "records": [{"date": "2022-08-07", "area_id": "muong_nhe", "lat": 22.2169654, "lon": 102.4203498, "year": 2022, "month": 8, "day": 7, "temperature_2m_max": 26.0, "temperature_2m_min": 21.9, "temperature_2m_mean": 23.5, "apparent_temperature_max": 31.8, "apparent_temperature_min": 26.5, "apparent_temperature_mean": 28.6, "precipitation_sum": 34.3, "rain_sum": 34.3, "precipitation_hours": 19.0, "weather_code": 63.0, "shortwave_radiation_sum": 11.1, "et0_fao_evapotranspiration": 2.16, "daylight_duration": 46976.18, "sunshine_duration": 16466.51, "uv_index_max": null, "wind_speed_10m_max": 8.8, "wind_gusts_10m_max": 28.8, "wind_direction_10m_dominant": 134.0, "relative_humidity_2m_mean": 97.0, "surface_pressure_mean": 939.4}]}