{"metadata": {"fetched_at": "2026-07-18T15:15:35.328087", "area_id": "muong_nhe", "source": "open-meteo/archive-api (batch)"}, "records": [{"date": "2016-02-08", "area_id": "muong_nhe", "lat": 22.2169654, "lon": 102.4203498, "year": 2016, "month": 2, "day": 8, "temperature_2m_max": 19.8, "temperature_2m_min": 10.3, "temperature_2m_mean": 14.8, "apparent_temperature_max": 19.9, "apparent_temperature_min": 9.7, "apparent_temperature_mean": 14.3, "precipitation_sum": 0.0, "rain_sum": 0.0, "precipitation_hours": 0.0, "weather_code": 3.0, "shortwave_radiation_sum": 19.03, "et0_fao_evapotranspiration": 3.15, "daylight_duration": 40590.31, "sunshine_duration": 39535.27, "uv_index_max": null, "wind_speed_10m_max": 7.0, "wind_gusts_10m_max": 21.2, "wind_direction_10m_dominant": 119.0, "relative_humidity_2m_mean": 71.0, "surface_pressure_mean": 951.5}]}