{"metadata": {"fetched_at": "2026-07-18T15:15:35.499642", "area_id": "muong_nhe", "source": "open-meteo/archive-api (batch)"}, "records": [{"date": "2018-06-19", "area_id": "muong_nhe", "lat": 22.2169654, "lon": 102.4203498, "year": 2018, "month": 6, "day": 19, "temperature_2m_max": 28.1, "temperature_2m_min": 22.0, "temperature_2m_mean": 24.9, "apparent_temperature_max": 33.9, "apparent_temperature_min": 26.7, "apparent_temperature_mean": 30.2, "precipitation_sum": 7.6, "rain_sum": 7.6, "precipitation_hours": 22.0, "weather_code": 55.0, "shortwave_radiation_sum": 14.94, "et0_fao_evapotranspiration": 3.06, "daylight_duration": 48576.35, "sunshine_duration": 22207.29, "uv_index_max": null, "wind_speed_10m_max": 7.6, "wind_gusts_10m_max": 26.3, "wind_direction_10m_dominant": 126.0, "relative_humidity_2m_mean": 92.0, "surface_pressure_mean": 936.9}]}