{"metadata": {"fetched_at": "2026-07-18T15:14:47.633518", "area_id": "commune_19537811", "source": "open-meteo/archive-api (batch)"}, "records": [{"date": "2013-05-07", "area_id": "commune_19537811", "lat": 22.3958973, "lon": 102.274572, "year": 2013, "month": 5, "day": 7, "temperature_2m_max": 24.1, "temperature_2m_min": 16.2, "temperature_2m_mean": 19.1, "apparent_temperature_max": 27.3, "apparent_temperature_min": 18.0, "apparent_temperature_mean": 21.5, "precipitation_sum": 11.4, "rain_sum": 11.4, "precipitation_hours": 13.0, "weather_code": 61.0, "shortwave_radiation_sum": 16.32, "et0_fao_evapotranspiration": 3.05, "daylight_duration": 47099.63, "sunshine_duration": 29681.46, "uv_index_max": null, "wind_speed_10m_max": 6.2, "wind_gusts_10m_max": 37.8, "wind_direction_10m_dominant": 134.0, "relative_humidity_2m_mean": 92.0, "surface_pressure_mean": 889.1}]}