{"metadata": {"fetched_at": "2026-07-18T15:14:47.601684", "area_id": "commune_19537811", "source": "open-meteo/archive-api (batch)"}, "records": [{"date": "2012-12-25", "area_id": "commune_19537811", "lat": 22.3958973, "lon": 102.274572, "year": 2012, "month": 12, "day": 25, "temperature_2m_max": 18.0, "temperature_2m_min": 9.0, "temperature_2m_mean": 13.5, "apparent_temperature_max": 17.8, "apparent_temperature_min": 8.5, "apparent_temperature_mean": 13.3, "precipitation_sum": 0.0, "rain_sum": 0.0, "precipitation_hours": 0.0, "weather_code": 3.0, "shortwave_radiation_sum": 10.48, "et0_fao_evapotranspiration": 1.76, "daylight_duration": 38754.65, "sunshine_duration": 33086.54, "uv_index_max": null, "wind_speed_10m_max": 6.2, "wind_gusts_10m_max": 19.4, "wind_direction_10m_dominant": 134.0, "relative_humidity_2m_mean": 83.0, "surface_pressure_mean": 892.2}]}