{"metadata": {"fetched_at": "2026-07-18T15:14:48.015376", "area_id": "commune_19537811", "source": "open-meteo/archive-api (batch)"}, "records": [{"date": "2018-09-26", "area_id": "commune_19537811", "lat": 22.3958973, "lon": 102.274572, "year": 2018, "month": 9, "day": 26, "temperature_2m_max": 26.5, "temperature_2m_min": 19.5, "temperature_2m_mean": 22.1, "apparent_temperature_max": 31.2, "apparent_temperature_min": 22.5, "apparent_temperature_mean": 26.1, "precipitation_sum": 6.5, "rain_sum": 6.5, "precipitation_hours": 13.0, "weather_code": 61.0, "shortwave_radiation_sum": 14.88, "et0_fao_evapotranspiration": 2.88, "daylight_duration": 43393.85, "sunshine_duration": 25642.2, "uv_index_max": null, "wind_speed_10m_max": 4.7, "wind_gusts_10m_max": 26.3, "wind_direction_10m_dominant": 112.0, "relative_humidity_2m_mean": 94.0, "surface_pressure_mean": 889.9}]}